{
    "breadcrumbs": [
        {
            "path": "/mn-samples-plateau-firelight-demo/002/tocE_03",
            "plainTitle": "E.3  標準的な作業手順"
        },
        {
            "path": "/mn-samples-plateau-firelight-demo/002/",
            "plainTitle": "PLATEAU 2"
        }
    ],
    "children": [
        {
            "path": "/mn-samples-plateau-firelight-demo/002/tocE_03/幾何オブジェクトの作成__3/_lod0_6",
            "plainTitle": "E.3.1.1  LOD0"
        },
        {
            "path": "/mn-samples-plateau-firelight-demo/002/tocE_03/幾何オブジェクトの作成__3/_lod1_6",
            "plainTitle": "E.3.1.2  LOD1"
        },
        {
            "path": "/mn-samples-plateau-firelight-demo/002/tocE_03/幾何オブジェクトの作成__3/_lod2_6",
            "plainTitle": "E.3.1.3  LOD2"
        },
        {
            "path": "/mn-samples-plateau-firelight-demo/002/tocE_03/幾何オブジェクトの作成__3/_lod3_0_2",
            "plainTitle": "E.3.1.4  LOD3.0"
        },
        {
            "path": "/mn-samples-plateau-firelight-demo/002/tocE_03/幾何オブジェクトの作成__3/_lod3_1_2",
            "plainTitle": "E.3.1.5  LOD3.1"
        },
        {
            "path": "/mn-samples-plateau-firelight-demo/002/tocE_03/幾何オブジェクトの作成__3/_lod3_2_3",
            "plainTitle": "E.3.1.6  LOD3.2"
        }
    ]
}