{
    "adapterID": "file:/Volumes/MNFirelight/firelight/packages/metanorma-site-content",
    "content": {
        "primaryLanguageID": "ja",
        "labelInPlainText": "N.2.4.1  分類（uro:class）、機能（uro:function）",
        "title": {
            "type": "doc",
            "content": [
                {
                    "type": "text",
                    "text": "N.2.4.1  分類（uro:class）、機能（uro:function）"
                }
            ]
        },
        "contentSchemaID": "clause",
        "contentDoc": {
            "type": "doc",
            "content": [
                {
                    "type": "title",
                    "content": [
                        {
                            "type": "text",
                            "text": "N.2.4.1  分類（uro:class）、機能（uro:function）"
                        }
                    ]
                },
                {
                    "type": "paragraph",
                    "attrs": {
                        "resourceID": "urn:x-metanorma-xml-id:_93f8e136-3932-314b-8f21-7840c2074329"
                    },
                    "content": [
                        {
                            "type": "text",
                            "text": "その他の構造物には、ダム、堤防、床止め、堰、水門・閘門・陸閘、樋門・樋管、伏せ越し、水制、護岸、防波堤その他の土木構造物が含まれるが、これらの区分は属性classにより行う。また、属性functionにより、細分できる。"
                        }
                    ]
                },
                {
                    "type": "paragraph",
                    "attrs": {
                        "resourceID": "urn:x-metanorma-xml-id:_226ae572-1398-ef3d-89db-f9b36306bf7a"
                    },
                    "content": [
                        {
                            "type": "text",
                            "text": "標準製品仕様書では、主に河川、港湾、漁港に関する構造物の区分をコードリストに用意しているが、不足する場合には、拡張製品仕様書において拡張できる。"
                        }
                    ]
                }
            ]
        }
    }
}