{
    "adapterID": "file:/Volumes/MNFirelight/firelight/packages/metanorma-site-content",
    "content": {
        "primaryLanguageID": "ja",
        "labelInPlainText": "S.2.4.1  データ品質属性（uro:DataQualityAttribute）",
        "title": {
            "type": "doc",
            "content": [
                {
                    "type": "text",
                    "text": "S.2.4.1  データ品質属性（uro:DataQualityAttribute）"
                }
            ]
        },
        "contentSchemaID": "clause",
        "contentDoc": {
            "type": "doc",
            "content": [
                {
                    "type": "title",
                    "content": [
                        {
                            "type": "text",
                            "text": "S.2.4.1  データ品質属性（uro:DataQualityAttribute）"
                        }
                    ]
                },
                {
                    "type": "paragraph",
                    "attrs": {
                        "resourceID": "urn:x-metanorma-xml-id:_28b5fe5f-278f-dab6-8315-f4f0ff5d79a4"
                    },
                    "content": [
                        {
                            "type": "text",
                            "text": "使用した原典資料やそれに基づくデータの品質、また、採用したLODは、データセットのメタデータに記録できる。ただし、データセット全体に対して一つのメタデータを作成することが基本となり、個々の都市オブジェクトの品質を記録することは困難である。"
                        }
                    ]
                },
                {
                    "type": "paragraph",
                    "attrs": {
                        "resourceID": "urn:x-metanorma-xml-id:_090a1571-3f93-0576-6e9d-cc99a36ad6dc"
                    },
                    "content": [
                        {
                            "type": "text",
                            "text": "そこで、標準製品仕様書では、個々のデータに対してデータ品質に関する情報を記述するための属性として、「データ品質属性」（uro:DataQualityAttribute）を定義している。データ品質属性は、属性としてデータ作成に使用した原典資料の地図情報レベル、その他原典資料の諸元及び精緻化したLODをもつ。"
                        }
                    ]
                },
                {
                    "type": "paragraph",
                    "attrs": {
                        "resourceID": "urn:x-metanorma-xml-id:_26831c5b-bd2e-11b8-81c0-31a952f3505b"
                    },
                    "content": [
                        {
                            "type": "text",
                            "text": "3D都市モデルに含まれる全ての地形オブジェクトは、このデータ品質属性を必ず作成しなければならない。"
                        }
                    ]
                }
            ]
        }
    }
}