{
    "adapterID": "file:/Volumes/MNFirelight/firelight/packages/metanorma-site-content",
    "content": {
        "primaryLanguageID": "ja",
        "labelInPlainText": "F.2.4  徒歩道の主題属性",
        "title": {
            "type": "doc",
            "content": [
                {
                    "type": "text",
                    "text": "F.2.4  徒歩道の主題属性"
                }
            ]
        },
        "contentSchemaID": "clause",
        "contentDoc": {
            "type": "doc",
            "content": [
                {
                    "type": "title",
                    "content": [
                        {
                            "type": "text",
                            "text": "F.2.4  徒歩道の主題属性"
                        }
                    ]
                },
                {
                    "type": "paragraph",
                    "attrs": {
                        "resourceID": "urn:x-metanorma-xml-id:_51ae497c-b247-44cf-d4cf-71c5186f667d"
                    },
                    "content": [
                        {
                            "type": "text",
                            "text": "徒歩道の主題属性には、あらかじめCityGML又はGMLにおいて定義された属性（接頭辞tran、gml）と、i-URにより拡張された属性（接頭辞uro）がある。CityGMLで定義された属性は、道路の機能など、基本的な情報となる。i-URにより拡張された属性には、徒歩道に関する情報を格納するための属性（uro:TrackAttribute）、数値地形図との互換性を保つための情報を格納するための属性（uro:DmAttribute）、さらに、作成したデータの品質に関する情報を格納するための属性（uro:DataQualityAttribute）がある。"
                        }
                    ]
                }
            ]
        }
    }
}